bntrans/__init__.py
bntrans/cli.py
bntrans/translator.py
bntrans/pysbd/__init__.py
bntrans/pysbd/abbreviation_replacer.py
bntrans/pysbd/about.py
bntrans/pysbd/between_punctuation.py
bntrans/pysbd/cleaner.py
bntrans/pysbd/exclamation_words.py
bntrans/pysbd/languages.py
bntrans/pysbd/lists_item_replacer.py
bntrans/pysbd/processor.py
bntrans/pysbd/punctuation_replacer.py
bntrans/pysbd/segmenter.py
bntrans/pysbd/utils.py
bntrans/pysbd/clean/__init__.py
bntrans/pysbd/clean/rules.py
bntrans/pysbd/lang/__init__.py
bntrans/pysbd/lang/amharic.py
bntrans/pysbd/lang/arabic.py
bntrans/pysbd/lang/armenian.py
bntrans/pysbd/lang/bangla.py
bntrans/pysbd/lang/bulgarian.py
bntrans/pysbd/lang/burmese.py
bntrans/pysbd/lang/chinese.py
bntrans/pysbd/lang/danish.py
bntrans/pysbd/lang/deutsch.py
bntrans/pysbd/lang/dutch.py
bntrans/pysbd/lang/english.py
bntrans/pysbd/lang/french.py
bntrans/pysbd/lang/greek.py
bntrans/pysbd/lang/hindi.py
bntrans/pysbd/lang/italian.py
bntrans/pysbd/lang/japanese.py
bntrans/pysbd/lang/kazakh.py
bntrans/pysbd/lang/marathi.py
bntrans/pysbd/lang/persian.py
bntrans/pysbd/lang/polish.py
bntrans/pysbd/lang/russian.py
bntrans/pysbd/lang/slovak.py
bntrans/pysbd/lang/spanish.py
bntrans/pysbd/lang/urdu.py
bntrans/pysbd/lang/common/__init__.py
bntrans/pysbd/lang/common/common.py
bntrans/pysbd/lang/common/standard.py
bntrans/tools/__init__.py
bntrans-0.0.5.dist-info/LICENSE
bntrans-0.0.5.dist-info/METADATA
bntrans-0.0.5.dist-info/WHEEL
bntrans-0.0.5.dist-info/entry_points.txt
bntrans-0.0.5.dist-info/top_level.txt
bntrans-0.0.5.dist-info/RECORD
