Metadata-Version: 2.1
Name: bntrans
Version: 0.0.5
Summary: BanglaTranslationKit: Open-source tool for offline Bangla-English translation.
Home-page: https://github.com/shhossain/BanglaTranslationKit
Author: shhossain
Author-email: 
Keywords: bangla,english,translation,nlp,machine-translation,bangla to english translation,english to bangla translation
Classifier: Development Status :: 1 - Planning
Classifier: Intended Audience :: Developers
Classifier: Intended Audience :: Education
Classifier: Intended Audience :: Science/Research
Classifier: Topic :: Scientific/Engineering :: Artificial Intelligence
Classifier: Topic :: Text Processing :: Linguistic
Classifier: Programming Language :: Python :: 3
Requires-Python: >=3.6
License-File: LICENSE
Requires-Dist: transformers
Requires-Dist: sentencepiece (==0.1.99)
Requires-Dist: sacremoses (==0.0.53)
Requires-Dist: torch
